{
  "session_id": "session-2026-04-29-2122",
  "started": "2026-04-29T01:22:41.167Z",
  "files_read": {
    "/Users/mosorio/repos/mint/graphql_engine/.github/workflows/docker-publish.yml": {
      "count": 1,
      "tokens": 0,
      "first_read": "2026-04-29T01:23:45.717Z"
    },
    "/Users/mosorio/repos/mint/mint-ensemble-manager/.github/workflows/docker-publish.yml": {
      "count": 1,
      "tokens": 2077,
      "first_read": "2026-04-29T01:23:51.893Z"
    },
    "/Users/mosorio/repos/mint/helm-charts/dynamo-values.yaml": {
      "count": 1,
      "tokens": 609,
      "first_read": "2026-04-29T02:15:53.369Z"
    }
  },
  "files_written": [
    {
      "file": "/Users/mosorio/repos/mint/.planning/phases/12-model-catalog-configuration-file-input-tapis-compatibility/.continue-here.md",
      "action": "create",
      "tokens": 1366,
      "at": "2026-04-29T01:22:47.493Z"
    },
    {
      "file": "/Users/mosorio/repos/mint/mint-ensemble-manager/.github/workflows/docker-publish.yml",
      "action": "edit",
      "tokens": 29,
      "at": "2026-04-29T01:25:53.289Z"
    },
    {
      "file": "/Users/mosorio/repos/mint/graphql_engine/.github/workflows/docker-publish.yml",
      "action": "edit",
      "tokens": 22,
      "at": "2026-04-29T01:25:59.819Z"
    },
    {
      "file": "/Users/mosorio/repos/mint/graphql_engine/.github/workflows/docker-publish.yml",
      "action": "edit",
      "tokens": 150,
      "at": "2026-04-29T01:26:38.963Z"
    },
    {
      "file": "/Users/mosorio/repos/mint/graphql_engine/.github/workflows/docker-publish.yml",
      "action": "edit",
      "tokens": 54,
      "at": "2026-04-29T01:27:24.661Z"
    },
    {
      "file": "/Users/mosorio/repos/mint/mint-ensemble-manager/src/api/api-v1/paths/problemStatements/tasks/subtasks/executions/index.ts",
      "action": "edit",
      "tokens": 243,
      "at": "2026-04-29T01:40:02.874Z"
    },
    {
      "file": "/Users/mosorio/repos/mint/helm-charts/dynamo-values.yaml",
      "action": "edit",
      "tokens": 36,
      "at": "2026-04-29T02:15:56.713Z"
    }
  ],
  "edit_counts": {
    ".planning/phases/12-model-catalog-configuration-file-input-tapis-compatibility/.continue-here.md": 1,
    "mint-ensemble-manager/.github/workflows/docker-publish.yml": 1,
    "graphql_engine/.github/workflows/docker-publish.yml": 3,
    "mint-ensemble-manager/src/api/api-v1/paths/problemStatements/tasks/subtasks/executions/index.ts": 1,
    "helm-charts/dynamo-values.yaml": 1
  },
  "anatomy_hits": 2,
  "anatomy_misses": 1,
  "repeated_reads_warned": 0,
  "cerebrum_warnings": 0,
  "stop_count": 8
}